Workbook

Sheet 1. Calculador de Obra
A1: SISTEMA OPERATIVO DE PRESUPUESTOS Y CONTROL DE MARGEN — OBRA PRO SUITE
A3: Cliente: | B3: Reforma Vivienda D. Juan García | D3: Fecha: | E3: =TODAY()
A4: Dirección Obra: | B4: Calle Mayor 14, 3ºB | D4: Validez Presupuesto: | E4: 30 días
A6: CONFIGURACIÓN FINANCIERA DE LA OBRA
A7: Margen Neto Deseado: | B7: 0.3
A8: Colchón de Imprevistos y Mermas: | B8: 0.1
A9: Gastos Generales / Furgoneta / Seguros: | B9: 0.08
A10: Tipo de IVA: | B10: 0.1
A12: Capítulo / Partida | B12: Medición | C12: Unidad | D12: Coste Material Unit. | E12: Horas M.O. | F12: Coste Hora M.O. | G12: Coste Directo Total | H12: PVP Venta al Cliente
A13: Demolición de alicatado, sanitarios y retirada escombros a vertedero | B13: 25 | C13: m² | D13: 4.5 | E13: 16 | F13: 25 | G13: =(B13*D13)+(E13*F13) | H13: =G13*(1+$B$8+$B$9)/(1-$B$7)
A14: Instalación de fontanería completa baño (multicapa + desagües) | B14: 1 | C14: ud | D14: 240 | E14: 14 | F14: 28 | G14: =(B14*D14)+(E14*F14) | H14: =G14*(1+$B$8+$B$9)/(1-$B$7)
A15: Suministro y colocación de gres porcelánico rectificado | B15: 25 | C15: m² | D15: 22 | E15: 20 | F15: 26 | G15: =(B15*D15)+(E15*F15) | H15: =G15*(1+$B$8+$B$9)/(1-$B$7)
A16: Plato de ducha resina 120x80 + mampara vidrio templado 8mm | B16: 1 | C16: ud | D16: 410 | E16: 6 | F16: 28 | G16: =(B16*D16)+(E16*F16) | H16: =G16*(1+$B$8+$B$9)/(1-$B$7)
A17: Instalación eléctrica baño: 3 downlights LED + enchufe estanco | B17: 1 | C17: ud | D17: 85 | E17: 5 | F17: 28 | G17: =(B17*D17)+(E17*F17) | H17: =G17*(1+$B$8+$B$9)/(1-$B$7)
A18: Montaje de mueble lavabo suspendido 80cm con espejo LED e inodoro | B18: 1 | C18: ud | D18: 380 | E18: 5 | F18: 26 | G18: =(B18*D18)+(E18*F18) | H18: =G18*(1+$B$8+$B$9)/(1-$B$7)
A19: Pintura plástica lisa antimoho en techo | B19: 6 | C19: m² | D19: 3 | E19: 3 | F19: 24 | G19: =(B19*D19)+(E19*F19) | H19: =G19*(1+$B$8+$B$9)/(1-$B$7)
A21: TOTALES OBRA / REFORMA | G21: =SUM(G13:G19) | H21: =SUM(H13:H19)
F23: COSTE DIRECTO MATERIALES + M.O.: | H23: =G21
F24: BENEFICIO LIMPIO ESTIMADO (MARGEN NETO): | H24: =H21-G21-(H21*$B$9)
F25: BASE IMPONIBLE PRESUPUESTO CLIENTE: | H25: =H21
F26: IVA (10%): | H26: =H25*$B$10
F27: TOTAL CON IVA A COBRAR: | H27: =H25+H26

Sheet 2. Presupuesto para Cliente
A1: PRESUPUESTO DE REFORMA | F1: Nº PRESUPUESTO: REF-2026-084
A3: DATOS DE LA EMPRESA / PROFESIONAL | E3: DATOS DEL CLIENTE
A4: Reformas & Construcciones Profesionales S.L. | E4: ='1. Calculador de Obra'!B3
A5: NIF/CIF: B-12345678 | E5: ='1. Calculador de Obra'!B4
A6: Tel: 600 000 000 | Email: info@tuempresa.es | E6: Fecha emisión: =TODAY()
A8: Nº | B8: DESCRIPCIÓN DE LA PARTIDA | C8: CANTIDAD | D8: UNIDAD | E8: PRECIO PVP
A9: 1 | B9: ='1. Calculador de Obra'!A13 | C9: ='1. Calculador de Obra'!B13 | D9: ='1. Calculador de Obra'!C13 | E9: ='1. Calculador de Obra'!H13
A10: 2 | B10: ='1. Calculador de Obra'!A14 | C10: ='1. Calculador de Obra'!B14 | D10: ='1. Calculador de Obra'!C14 | E10: ='1. Calculador de Obra'!H14
A11: 3 | B11: ='1. Calculador de Obra'!A15 | C11: ='1. Calculador de Obra'!B15 | D11: ='1. Calculador de Obra'!C15 | E11: ='1. Calculador de Obra'!H15
A12: 4 | B12: ='1. Calculador de Obra'!A16 | C12: ='1. Calculador de Obra'!B16 | D12: ='1. Calculador de Obra'!C16 | E12: ='1. Calculador de Obra'!H16
A13: 5 | B13: ='1. Calculador de Obra'!A17 | C13: ='1. Calculador de Obra'!B17 | D13: ='1. Calculador de Obra'!C17 | E13: ='1. Calculador de Obra'!H17
A14: 6 | B14: ='1. Calculador de Obra'!A18 | C14: ='1. Calculador de Obra'!B18 | D14: ='1. Calculador de Obra'!C18 | E14: ='1. Calculador de Obra'!H18
A15: 7 | B15: ='1. Calculador de Obra'!A19 | C15: ='1. Calculador de Obra'!B19 | D15: ='1. Calculador de Obra'!C19 | E15: ='1. Calculador de Obra'!H19
D17: BASE IMPONIBLE: | E17: =SUM(E9:E15)
D18: IVA (10%): | E18: =E17*0.10
D19: TOTAL PRESUPUESTO: | E19: =E17+E18
A21: CONDICIONES Y FORMA DE PAGO:
A22: 1. 40% a la firma del contrato y acopio de materiales.
A23: 2. 40% al 50% de avance de los trabajos de albañilería e instalaciones.
A24: 3. 20% a la finalización y entrega de llaves.
A25: 4. Validez de la oferta: 30 días a partir de la fecha de emisión.
B27: Firma Empresa: | D27: Conforme Cliente:

Sheet 3. Catálogo Precios Base
A1: Categoría | B1: Descripción Partida | C1: Unidad | D1: Coste Material Ref. | E1: Horas Estimadas
A2: Demolición | B2: Picado de solera o recrecido de hormigón hasta 10cm | C2: m² | D2: 2 | E2: 1.2
A3: Demolición | B3: Derribo de tabique de ladrillo hueco sencillo/doble | C3: m² | D3: 1.5 | E3: 0.8
A4: Albañilería | B4: Levantado de tabique ladrillo cerámico 7cm | C4: m² | D4: 9.5 | E4: 1.5
A5: Albañilería | B5: Enlucido y maestreado con yeso o mortero | C5: m² | D5: 4 | E5: 1.1
A6: Albañilería | B6: Recrecido y nivelación de suelo con mortero | C6: m² | D6: 5.5 | E6: 0.7
A7: Pladur / Cartón-Yeso | B7: Tabique pladur doble placa con aislamiento acústico | C7: m² | D7: 18 | E7: 1.3
A8: Pladur / Cartón-Yeso | B8: Falso techo continuo pladur con perfilería | C8: m² | D8: 14 | E8: 1
A9: Alicatados | B9: Alicatado de paredes con mortero cola flexible C2TE | C9: m² | D9: 8 | E9: 1.2
A10: Solados | B10: Colocación de suelo porcelánico gran formato | C10: m² | D10: 11 | E10: 1.4
A11: Fontanería | B11: Punto de agua fría y caliente en multicapa/PEX | C11: ud | D11: 25 | E11: 1.8
A12: Fontanería | B12: Punto de desagüe PVC insonorizado | C12: ud | D12: 18 | E12: 1.2
A13: Electricidad | B13: Punto de luz / interruptor con tubo corrugado y cableado | C13: ud | D13: 12 | E13: 1
... A19: Carpintería | B19: Montaje de rodapié lacado blanco o madera | C19: ml | D19: 3 | E19: 0.3
